html_section/__init__.py
html_section/py.typed
html_section-0.3.0.dist-info/LICENSE
html_section-0.3.0.dist-info/METADATA
html_section-0.3.0.dist-info/WHEEL
html_section-0.3.0.dist-info/entry_points.txt
html_section-0.3.0.dist-info/RECORD
