Metadata-Version: 2.1
Name: html-section
Version: 0.3.0
Summary: Sphinx extension to hide section headers with non-HTML builders.
Author-email: Dominic Davis-Foster <dominic@davis-foster.co.uk>
License: BSD-3-Clause
Keywords: documentation,sphinx,sphinx-extension
Home-page: https://github.com/sphinx-toolbox/html-section
Project-URL: Issue Tracker, https://github.com/sphinx-toolbox/html-section/issues
Project-URL: Source Code, https://github.com/sphinx-toolbox/html-section
Platform: Windows
Platform: macOS
Platform: Linux
Classifier: Development Status :: 3 - Alpha
Classifier: Framework :: Sphinx :: Extension
Classifier: Intended Audience :: Developers
Classifier: License :: OSI Approved :: BSD License
Classifier: Operating System :: OS Independent
Classifier: Programming Language :: Python
Classifier: Programming Language :: Python :: 3 :: Only
Classifier: Programming Language :: Python :: 3.6
Classifier: Programming Language :: Python :: 3.7
Classifier: Programming Language :: Python :: 3.8
Classifier: Programming Language :: Python :: 3.9
Classifier: Programming Language :: Python :: 3.10
Classifier: Programming Language :: Python :: Implementation :: CPython
Classifier: Topic :: Documentation
Classifier: Topic :: Documentation :: Sphinx
Classifier: Topic :: Software Development :: Documentation
Classifier: Topic :: Utilities
Classifier: Typing :: Typed
Requires-Python: >=3.6
Requires-Dist: docutils>=0.16
Requires-Dist: sphinx>=3.3.0
Requires-Dist: sphinx-jinja2-compat>=0.1.2
